petitgrad/__init__.py
petitgrad/engine.py
petitgrad/nn.py
tests/__init__.py
tests/test_engine.py
tests/test_nn.py
petitgrad-0.1.1.dist-info/LICENCE
petitgrad-0.1.1.dist-info/METADATA
petitgrad-0.1.1.dist-info/WHEEL
petitgrad-0.1.1.dist-info/top_level.txt
petitgrad-0.1.1.dist-info/RECORD
