Metadata-Version: 2.1
Name: petitgrad
Version: 0.1.1
Summary: A tiny or petit autograd engine with matrix operations, based on Andrej Karpathy's micrograd.
Home-page: https://github.com/bcivitcioglu/petitgrad
Author: Burak Ç.
Author-email: bcivitcioglu@gmail.com
Classifier: Programming Language :: Python :: 3
Classifier: License :: OSI Approved :: MIT License
Classifier: Operating System :: OS Independent
License-File: LICENCE
Requires-Dist: numpy
